foragax/__init__.py
foragax/colors.py
foragax/env.py
foragax/objects.py
foragax/registry.py
foragax/rendering.py
foragax/weather.py
foragax/data/ECA_non-blended_custom/TG_SOUID100897.txt
foragax/data/ECA_non-blended_custom/TG_SOUID100928.txt
foragax/data/ECA_non-blended_custom/TG_SOUID100929.txt
foragax/data/ECA_non-blended_custom/TG_SOUID100930.txt
foragax/data/ECA_non-blended_custom/TG_SOUID100931.txt
foragax/data/ECA_non-blended_custom/TG_SOUID106714.txt
foragax/data/ECA_non-blended_custom/TG_SOUID106715.txt
foragax/data/ECA_non-blended_custom/TG_SOUID106716.txt
foragax/data/ECA_non-blended_custom/TG_SOUID106717.txt
foragax/data/ECA_non-blended_custom/TG_SOUID106718.txt
foragax/data/ECA_non-blended_custom/TG_SOUID106930.txt
foragax/data/ECA_non-blended_custom/TG_SOUID106931.txt
foragax/data/ECA_non-blended_custom/TG_SOUID106932.txt
foragax/data/ECA_non-blended_custom/TG_SOUID106933.txt
foragax/data/ECA_non-blended_custom/TG_SOUID106934.txt
foragax/data/ECA_non-blended_custom/TG_SOUID106935.txt
foragax/data/ECA_non-blended_custom/TG_SOUID106936.txt
foragax/data/ECA_non-blended_custom/TG_SOUID106937.txt
foragax/data/ECA_non-blended_custom/TG_SOUID106938.txt
foragax/data/ECA_non-blended_custom/TG_SOUID106939.txt
foragax/data/ECA_non-blended_custom/TG_SOUID106940.txt
foragax/data/ECA_non-blended_custom/TG_SOUID106941.txt
foragax/data/ECA_non-blended_custom/TG_SOUID106942.txt
foragax/data/ECA_non-blended_custom/TG_SOUID106943.txt
foragax/data/ECA_non-blended_custom/TG_SOUID106994.txt
foragax/data/ECA_non-blended_custom/TG_SOUID106995.txt
foragax/data/ECA_non-blended_custom/TG_SOUID106996.txt
foragax/data/ECA_non-blended_custom/TG_SOUID106997.txt
foragax/data/ECA_non-blended_custom/TG_SOUID106998.txt
foragax/data/ECA_non-blended_custom/TG_SOUID106999.txt
foragax/data/ECA_non-blended_custom/TG_SOUID107000.txt
foragax/data/ECA_non-blended_custom/TG_SOUID107001.txt
foragax/data/ECA_non-blended_custom/TG_SOUID107002.txt
continual_foragax-0.42.1.dist-info/METADATA
continual_foragax-0.42.1.dist-info/WHEEL
continual_foragax-0.42.1.dist-info/entry_points.txt
continual_foragax-0.42.1.dist-info/top_level.txt
continual_foragax-0.42.1.dist-info/RECORD
