Metadata-Version: 2.4
Name: continual-foragax
Version: 0.42.1
Summary: A continual reinforcement learning benchmark
Author-email: Steven Tang <stang5@ualberta.ca>
Requires-Python: >=3.8
Requires-Dist: gymnax
Requires-Dist: six; python_version < "3.10"
